nontopus/__init__.py
nontopus/data_utils.py
nontopus-0.1.2.dist-info/licenses/LICENSE
nontopus-0.1.2.dist-info/METADATA
nontopus-0.1.2.dist-info/WHEEL
nontopus-0.1.2.dist-info/top_level.txt
nontopus-0.1.2.dist-info/RECORD
