Metadata-Version: 2.4
Name: nontopus
Version: 0.1.2
Summary: nontopus test library
Author-email: nontopus <micahb.yarbrough@gmail.com>
Requires-Python: >=3.8
License-File: LICENSE
Requires-Dist: numpy
Requires-Dist: pandas
Requires-Dist: openpyxl
Dynamic: license-file
